carbon_txt_validator/__init__.py
carbon_txt_validator/cli.py
carbon_txt_validator/finders.py
carbon_txt_validator/parsers_toml.py
carbon_txt_validator/schemas.py
carbon_txt_validator/web/db.sqlite3
carbon_txt_validator/web/manage.py
carbon_txt_validator/web/middleware.py
carbon_txt_validator/web/config/__init__.py
carbon_txt_validator/web/config/api.py
carbon_txt_validator/web/config/asgi.py
carbon_txt_validator/web/config/urls.py
carbon_txt_validator/web/config/wsgi.py
carbon_txt_validator/web/config/settings/__init__.py
carbon_txt_validator/web/config/settings/base.py
carbon_txt_validator/web/config/settings/development.py
carbon_txt_validator/web/config/settings/production.py
carbon_txt_validator/web/config/settings/test.py
carbon_txt_validator-0.0.4.dist-info/METADATA
carbon_txt_validator-0.0.4.dist-info/WHEEL
carbon_txt_validator-0.0.4.dist-info/entry_points.txt
carbon_txt_validator-0.0.4.dist-info/RECORD
