Metadata-Version: 2.3
Name: carbon-txt-validator
Version: 0.0.4
Summary: A validator for carbon.txt files, by the Green Web Foundation
Author: Chris Adams, Hannah Smith, Fershad Irani
License: Apache-2.0
Classifier: License :: OSI Approved :: Apache Software License
Requires-Python: >=3.11
Requires-Dist: django-cors-headers>=4.6.0
Requires-Dist: django-environ>=0.11.2
Requires-Dist: django-ninja>=1.3.0
Requires-Dist: dnspython>=2.7.0
Requires-Dist: granian>=1.6.2
Requires-Dist: httpx>=0.27.2
Requires-Dist: rich>=13.9.2
Requires-Dist: typer>=0.12.5
